README.md
setup.cfg
setup.py
YouDown.egg-info/PKG-INFO
YouDown.egg-info/SOURCES.txt
YouDown.egg-info/dependency_links.txt
YouDown.egg-info/requires.txt
YouDown.egg-info/top_level.txt
youdown/__init__.py
youdown/youdown.py
youdown.egg-info/PKG-INFO
youdown.egg-info/SOURCES.txt
youdown.egg-info/dependency_links.txt
youdown.egg-info/entry_points.txt
youdown.egg-info/not-zip-safe
youdown.egg-info/requires.txt
youdown.egg-info/top_level.txt