Metadata-Version: 1.2
Name: youdown
Version: 1.0.1
Summary: YouDown is a simple way do download video in youtube using pytube and convert using ffmpeg.
Home-page: https://github.com/NatanielBR/YouDown
Author: Neoold
Author-email: 
License: MIT
Platform: UNKNOWN
Requires-Python: >=3
